{
  "uid" : "63670e429eafe6c",
  "name" : "T04fullSearchBasicTest[ogre]",
  "title" : "Full search basic test",
  "time" : {
    "start" : 1497875869442,
    "stop" : 1497875882582,
    "duration" : 13140
  },
  "summary" : {
    "attachments" : 0,
    "steps" : 0
  },
  "failure" : null,
  "description" : null,
  "severity" : "NORMAL",
  "status" : "PASSED",
  "suite" : {
    "uid" : "c48dd28a317703a1",
    "name" : "Happy Path Tests : org.no.cases.HappyPathTests",
    "title" : "Happy Path Tests : org.no.cases.HappyPathTests"
  },
  "steps" : [ ],
  "attachments" : [ ],
  "issues" : [ ],
  "testIds" : [ ],
  "labels" : [ {
    "name" : "thread",
    "value" : "19567@astrashevskiy2-wf.local.main(1)"
  }, {
    "name" : "feature",
    "value" : "Full search basic"
  }, {
    "name" : "suite-name",
    "value" : "Happy Path Tests : org.no.cases.HappyPathTests"
  }, {
    "name" : "host",
    "value" : "astrashevskiy2-wf.local"
  }, {
    "name" : "framework",
    "value" : "TestNG"
  }, {
    "name" : "testMethod",
    "value" : "T04fullSearchBasicTest"
  }, {
    "name" : "testClass",
    "value" : "org.no.cases.HappyPathTests"
  }, {
    "name" : "testSuite",
    "value" : "Happy Path Tests"
  }, {
    "name" : "language",
    "value" : "JAVA"
  }, {
    "name" : "severity",
    "value" : "normal"
  }, {
    "name" : "suite-title",
    "value" : "Happy Path Tests : org.no.cases.HappyPathTests"
  }, {
    "name" : "testGroup",
    "value" : "org.no.cases.HappyPathTests"
  } ],
  "parameters" : [ {
    "name" : "Search phrase",
    "value" : "ogre",
    "kind" : "ARGUMENT"
  } ]
}